{"title":"AFL.2015.Round.2.Hawthorn.vs.Essendon.PDTV.x264-CBFM","uid":11816681,"size":1619783966,"categoryP":"video","categoryS":"tv_shows","magnet":"?xt=urn:btih:201bdba6719a92a4ede2eacaaa5144c071a8de0f&amp;dn=AFL.2015.Round.2.Hawthorn.vs.Essendon.PDTV.x264-CBFM&amp;tr=udp%3A%2F%2Ftracker.openbittorrent.com%3A80&amp;tr=udp%3A%2F%2Fopen.demonii.com%3A1337&amp;tr=udp%3A%2F%2Ftracker.coppersurfer.tk%3A6969&amp;tr=udp%3A%2F%2Fexodus.desync.com%3A6969","seeders":0,"leechers":1,"uploader":"TvTeam","files":4,"time":1429115525,"description":"------------------------------------------------------------------------\n\n &lt;a href=&quot; https://www.torrenting.com&quot; rel=&quot;nofollow&quot; target=&quot;_NEW&quot;&gt; https://www.torrenting.com&lt;/a&gt;\n\nSign up is OPEN - for time being. Come and have fun","torrent":{"xt":"urn:btih:201bdba6719a92a4ede2eacaaa5144c071a8de0f","amp;dn":"AFL.2015.Round.2.Hawthorn.vs.Essendon.PDTV.x264-CBFM","amp;tr":["udp%3A%2F%2Ftracker.openbittorrent.com%3A80","udp%3A%2F%2Fopen.demonii.com%3A1337","udp%3A%2F%2Ftracker.coppersurfer.tk%3A6969","udp%3A%2F%2Fexodus.desync.com%3A6969"],"infoHash":"201bdba6719a92a4ede2eacaaa5144c071a8de0f","infoHashBuffer":{"type":"Buffer","data":[32,27,219,166,113,154,146,164,237,226,234,202,170,81,68,192,113,168,222,15]},"announce":[],"urlList":[]}}