{"title":"[BrazzersExxtra] Natalia Starr (Incognito Boss / 08.13.2014)","uid":10759545,"size":339811367,"categoryP":"porn","categoryS":"other","magnet":"?xt=urn:btih:2c57a8235d5cc0ab3614f4a3b51ec60afac6177c&amp;dn=%5BBrazzersExxtra%5D+Natalia+Starr+%28Incognito+Boss+%2F+08.13.2014%29&amp;tr=udp%3A%2F%2Ftracker.openbittorrent.com%3A80&amp;tr=udp%3A%2F%2Fopen.demonii.com%3A1337&amp;tr=udp%3A%2F%2Ftracker.coppersurfer.tk%3A6969&amp;tr=udp%3A%2F%2Fexodus.desync.com%3A6969","seeders":0,"leechers":0,"uploader":"TomcatX","files":1,"time":1407962820,"description":"[BrazzersExxtra] Natalia Starr (Incognito Boss / 08.13.2014)\n\nJohnny Sins is the CEO of Brazzers CafÃƒÆ’Ã‚Â©, and he's going undercover to spend a day posing as a lowly minimum wage sap in one of his locations. As soon as he gets there he can tell that this place isn't the well-oiled machine he thought it was. The waitresses are mistreating all the customers, and the manager Natalia Starr is making her waitresses have slutty competitions! Johnny puts an end to that and tells Natalia she's fired, but the slutty babe will do whatever it takes to save her job! She sucks and fucks his big dick while Johnny sucks, squeezes, and worships those big natural tits of hers, finally covering her pretty face in a nice gooey facial cumshot!\n\nScreens: &lt;a href=&quot;\nhttp://imgextra.biz/viewer.php?file=sexucv4x0v0yb80y4.jpg&quot; rel=&quot;nofollow&quot; target=&quot;_NEW&quot;&gt;\nhttp://imgextra.biz/viewer.php?file=sexucv4x0v0yb80y4.jpg&lt;/a&gt; &lt;a href=&quot;\nhttp://imgextra.biz/viewer.php?file=g6eu27tpgkd89qwsvi7y.jpg&quot; rel=&quot;nofollow&quot; target=&quot;_NEW&quot;&gt;\nhttp://imgextra.biz/viewer.php?file=g6eu27tpgkd89qwsvi7y.jpg&lt;/a&gt;","torrent":{"xt":"urn:btih:2c57a8235d5cc0ab3614f4a3b51ec60afac6177c","amp;dn":"%5BBrazzersExxtra%5D+Natalia+Starr+%28Incognito+Boss+%2F+08.13.2014%29","amp;tr":["udp%3A%2F%2Ftracker.openbittorrent.com%3A80","udp%3A%2F%2Fopen.demonii.com%3A1337","udp%3A%2F%2Ftracker.coppersurfer.tk%3A6969","udp%3A%2F%2Fexodus.desync.com%3A6969"],"infoHash":"2c57a8235d5cc0ab3614f4a3b51ec60afac6177c","infoHashBuffer":{"type":"Buffer","data":[44,87,168,35,93,92,192,171,54,20,244,163,181,30,198,10,250,198,23,124]},"announce":[],"urlList":[]}}