{"title":"aughtyAmerica - MyFriendsHotMom - Mikki Lynn *NEW September 1,20","uid":10945624,"size":272100402,"categoryP":"porn","categoryS":"other","magnet":"?xt=urn:btih:306a752f4257bb50eadf23cac0b67634d723cd27&amp;dn=aughtyAmerica+-+MyFriendsHotMom+-+Mikki+Lynn+%2ANEW+September+1%2C20&amp;tr=udp%3A%2F%2Ftracker.openbittorrent.com%3A80&amp;tr=udp%3A%2F%2Fopen.demonii.com%3A1337&amp;tr=udp%3A%2F%2Ftracker.coppersurfer.tk%3A6969&amp;tr=udp%3A%2F%2Fexodus.desync.com%3A6969","seeders":0,"leechers":0,"uploader":"SplashPt","files":4,"time":1409595743,"description":"N\nNaughtyAmerica - MyFriendsHotMom - Mikki Lynn -={SPARROW}=-\n &lt;a href=&quot;\nhttp://244pix.com/viewer.php?file=mffjg6wmq7uw.jpg&quot; rel=&quot;nofollow&quot; target=&quot;_NEW&quot;&gt;\nhttp://244pix.com/viewer.php?file=mffjg6wmq7uw.jpg&lt;/a&gt;","torrent":{"xt":"urn:btih:306a752f4257bb50eadf23cac0b67634d723cd27","amp;dn":"aughtyAmerica+-+MyFriendsHotMom+-+Mikki+Lynn+%2ANEW+September+1%2C20","amp;tr":["udp%3A%2F%2Ftracker.openbittorrent.com%3A80","udp%3A%2F%2Fopen.demonii.com%3A1337","udp%3A%2F%2Ftracker.coppersurfer.tk%3A6969","udp%3A%2F%2Fexodus.desync.com%3A6969"],"infoHash":"306a752f4257bb50eadf23cac0b67634d723cd27","infoHashBuffer":{"type":"Buffer","data":[48,106,117,47,66,87,187,80,234,223,35,202,192,182,118,52,215,35,205,39]},"announce":[],"urlList":[]}}