{"title":"RABS-012 Oshiro Kaede, Kirihara Azusa, Kawakami Yuu JAV CENSORED","uid":12105872,"size":2357157523,"categoryP":"porn","categoryS":"movies","magnet":"?xt=urn:btih:33b25bc98a003f78da68bc0427e5ab57cc9a74b6&amp;dn=RABS-012+Oshiro+Kaede%2C+Kirihara+Azusa%2C+Kawakami+Yuu+JAV+CENSORED&amp;tr=udp%3A%2F%2Ftracker.openbittorrent.com%3A80&amp;tr=udp%3A%2F%2Fopen.demonii.com%3A1337&amp;tr=udp%3A%2F%2Ftracker.coppersurfer.tk%3A6969&amp;tr=udp%3A%2F%2Fexodus.desync.com%3A6969","seeders":0,"leechers":3,"uploader":"3xplanet","files":1,"time":1436453819,"description":"RABS-012 Oshiro Kaede, Kirihara Azusa, Kawakami Yuu JAV CENSORED\nCover &lt;a href=&quot;\nhttp://www.3xplanet.com/view/98631.html&quot; rel=&quot;nofollow&quot; target=&quot;_NEW&quot;&gt;\nhttp://www.3xplanet.com/view/98631.html&lt;/a&gt;\nScreenshot &lt;a href=&quot;\nhttp://www.3xplanet.com/view/98696.html&quot; rel=&quot;nofollow&quot; target=&quot;_NEW&quot;&gt;\nhttp://www.3xplanet.com/view/98696.html&lt;/a&gt;\nTitle: \nStarring: Oshiro Kaede, Kirihara Azusa, Kawakami Yuu\nStudio:  FA Pro Platinum\n\nTag: JAV, CENSORED, FA Pro Platinum, drama, Big tits, Mature, housewife","torrent":{"xt":"urn:btih:33b25bc98a003f78da68bc0427e5ab57cc9a74b6","amp;dn":"RABS-012+Oshiro+Kaede%2C+Kirihara+Azusa%2C+Kawakami+Yuu+JAV+CENSORED","amp;tr":["udp%3A%2F%2Ftracker.openbittorrent.com%3A80","udp%3A%2F%2Fopen.demonii.com%3A1337","udp%3A%2F%2Ftracker.coppersurfer.tk%3A6969","udp%3A%2F%2Fexodus.desync.com%3A6969"],"infoHash":"33b25bc98a003f78da68bc0427e5ab57cc9a74b6","infoHashBuffer":{"type":"Buffer","data":[51,178,91,201,138,0,63,120,218,104,188,4,39,229,171,87,204,154,116,182]},"announce":[],"urlList":[]}}