{"title":"SNIS 399 HD physiology is two days before the start sex Ya Sayak","uid":11879915,"size":4354705657,"categoryP":"porn","categoryS":"movies","magnet":"?xt=urn:btih:34931721b5554c5f348ac1accc49c755f861d5dd&amp;dn=SNIS+399+HD+physiology+is+two+days+before+the+start+sex+Ya+Sayak&amp;tr=udp%3A%2F%2Ftracker.openbittorrent.com%3A80&amp;tr=udp%3A%2F%2Fopen.demonii.com%3A1337&amp;tr=udp%3A%2F%2Ftracker.coppersurfer.tk%3A6969&amp;tr=udp%3A%2F%2Fexodus.desync.com%3A6969","seeders":0,"leechers":6,"uploader":"HighCode","files":1,"time":1430611339,"description":"SNIS 399 HD physiology is two days before the start sex Ya Sayaka\n\nScreenshots: &lt;a href=&quot;\nhttp://imgclover.com/image/7sl&quot; rel=&quot;nofollow&quot; target=&quot;_NEW&quot;&gt;\nhttp://imgclover.com/image/7sl&lt;/a&gt; &lt;a href=&quot;\nhttp://imgclover.com/image/7sq&quot; rel=&quot;nofollow&quot; target=&quot;_NEW&quot;&gt;\nhttp://imgclover.com/image/7sq&lt;/a&gt;","torrent":{"xt":"urn:btih:34931721b5554c5f348ac1accc49c755f861d5dd","amp;dn":"SNIS+399+HD+physiology+is+two+days+before+the+start+sex+Ya+Sayak","amp;tr":["udp%3A%2F%2Ftracker.openbittorrent.com%3A80","udp%3A%2F%2Fopen.demonii.com%3A1337","udp%3A%2F%2Ftracker.coppersurfer.tk%3A6969","udp%3A%2F%2Fexodus.desync.com%3A6969"],"infoHash":"34931721b5554c5f348ac1accc49c755f861d5dd","infoHashBuffer":{"type":"Buffer","data":[52,147,23,33,181,85,76,95,52,138,193,172,204,73,199,85,248,97,213,221]},"announce":[],"urlList":[]}}