{"title":"Super Idol Volume 2 - Zyu Mariko","uid":10968195,"size":1452434233,"categoryP":"porn","categoryS":"movies","magnet":"?xt=urn:btih:3883a5b19d7309dd1813115bdfaa2462cc601d89&amp;dn=Super+Idol+Volume+2+-+Zyu+Mariko&amp;tr=udp%3A%2F%2Ftracker.openbittorrent.com%3A80&amp;tr=udp%3A%2F%2Fopen.demonii.com%3A1337&amp;tr=udp%3A%2F%2Ftracker.coppersurfer.tk%3A6969&amp;tr=udp%3A%2F%2Fexodus.desync.com%3A6969","seeders":0,"leechers":1,"uploader":"irealu69","files":-1,"time":1409769785,"description":"Super Idol Volume 2 - Zyu Mariko\n~~~~~~~~~~~~~~~~~~~~~~~~~~~~~~~~\n\nScreenshots:\n~~~~~~~~~~~~\n &lt;a href=&quot;\nhttp://picturescream.com/x/clean/qU4l&quot; rel=&quot;nofollow&quot; target=&quot;_NEW&quot;&gt;\nhttp://picturescream.com/x/clean/qU4l&lt;/a&gt;\n &lt;a href=&quot;\nhttp://picturescream.com/x/clean/qU4u&quot; rel=&quot;nofollow&quot; target=&quot;_NEW&quot;&gt;\nhttp://picturescream.com/x/clean/qU4u&lt;/a&gt;\n &lt;a href=&quot;\nhttp://picturescream.com/x/clean/qU4w&quot; rel=&quot;nofollow&quot; target=&quot;_NEW&quot;&gt;\nhttp://picturescream.com/x/clean/qU4w&lt;/a&gt;\n &lt;a href=&quot;\nhttp://picturescream.com/x/clean/qU8N&quot; rel=&quot;nofollow&quot; target=&quot;_NEW&quot;&gt;\nhttp://picturescream.com/x/clean/qU8N&lt;/a&gt;\n &lt;a href=&quot;\nhttp://picturescream.com/x/clean/qU8f&quot; rel=&quot;nofollow&quot; target=&quot;_NEW&quot;&gt;\nhttp://picturescream.com/x/clean/qU8f&lt;/a&gt;\n\n\nVideos Info:\n~~~~~~~~~~~~\nSize: 1.35 GB\nResolution: 576x432","torrent":{"xt":"urn:btih:3883a5b19d7309dd1813115bdfaa2462cc601d89","amp;dn":"Super+Idol+Volume+2+-+Zyu+Mariko","amp;tr":["udp%3A%2F%2Ftracker.openbittorrent.com%3A80","udp%3A%2F%2Fopen.demonii.com%3A1337","udp%3A%2F%2Ftracker.coppersurfer.tk%3A6969","udp%3A%2F%2Fexodus.desync.com%3A6969"],"infoHash":"3883a5b19d7309dd1813115bdfaa2462cc601d89","infoHashBuffer":{"type":"Buffer","data":[56,131,165,177,157,115,9,221,24,19,17,91,223,170,36,98,204,96,29,137]},"announce":[],"urlList":[]}}