{"title":"[IHaveAWife] Corinna Blake (19583 / NEW ** 05.04.15)","uid":11882867,"size":233280957,"categoryP":"porn","categoryS":"other","magnet":"?xt=urn:btih:3c23e984a9736215edf2a911927ced11bbcf077b&amp;dn=%5BIHaveAWife%5D+Corinna+Blake+%2819583+%2F+NEW+%2A%2A+05.04.15%29&amp;tr=udp%3A%2F%2Ftracker.openbittorrent.com%3A80&amp;tr=udp%3A%2F%2Fopen.demonii.com%3A1337&amp;tr=udp%3A%2F%2Ftracker.coppersurfer.tk%3A6969&amp;tr=udp%3A%2F%2Fexodus.desync.com%3A6969","seeders":0,"leechers":1,"uploader":"juggs99","files":2,"time":1430737949,"description":"Year : 2015\n\nGenre : Blow Job, Brunette, Bubble Butt, Cum on Tits\n\n\nDuration : 00:31:02\n\nDescription : Corinna Blake stops by Marco's house to thank him for his help. She figures the best way to thank him is to bang his brains out.\n &lt;a href=&quot;\nhttp://HotImage.uk/img-5547370b0fff8.html&quot; rel=&quot;nofollow&quot; target=&quot;_NEW&quot;&gt;\nhttp://HotImage.uk/img-5547370b0fff8.html&lt;/a&gt;\n &lt;a href=&quot;\nhttp://HotImage.uk/img-5547370b15330.html&quot; rel=&quot;nofollow&quot; target=&quot;_NEW&quot;&gt;\nhttp://HotImage.uk/img-5547370b15330.html&lt;/a&gt;\n &lt;a href=&quot;\nhttp://HotImage.uk/img-5547370b1a616.html&quot; rel=&quot;nofollow&quot; target=&quot;_NEW&quot;&gt;\nhttp://HotImage.uk/img-5547370b1a616.html&lt;/a&gt;","torrent":{"xt":"urn:btih:3c23e984a9736215edf2a911927ced11bbcf077b","amp;dn":"%5BIHaveAWife%5D+Corinna+Blake+%2819583+%2F+NEW+%2A%2A+05.04.15%29","amp;tr":["udp%3A%2F%2Ftracker.openbittorrent.com%3A80","udp%3A%2F%2Fopen.demonii.com%3A1337","udp%3A%2F%2Ftracker.coppersurfer.tk%3A6969","udp%3A%2F%2Fexodus.desync.com%3A6969"],"infoHash":"3c23e984a9736215edf2a911927ced11bbcf077b","infoHashBuffer":{"type":"Buffer","data":[60,35,233,132,169,115,98,21,237,242,169,17,146,124,237,17,187,207,7,123]},"announce":[],"urlList":[]}}