{"title":"Street Fighter Assassins Fist 2014 DVDRip x264 AC3-MiLLENiUM","uid":10797292,"size":1488480464,"categoryP":"video","categoryS":"movies","magnet":"?xt=urn:btih:3f58645ce91181bdcf81552b008104154e8c1e7d&amp;dn=Street+Fighter+Assassins+Fist+2014+DVDRip+x264+AC3-MiLLENiUM&amp;tr=udp%3A%2F%2Ftracker.openbittorrent.com%3A80&amp;tr=udp%3A%2F%2Fopen.demonii.com%3A1337&amp;tr=udp%3A%2F%2Ftracker.coppersurfer.tk%3A6969&amp;tr=udp%3A%2F%2Fexodus.desync.com%3A6969","seeders":0,"leechers":1,"uploader":"Drarbg","files":4,"time":1408306552,"description":" &lt;a href=&quot;https://rarbg.com&quot; rel=&quot;nofollow&quot; target=&quot;_NEW&quot;&gt;https://rarbg.com&lt;/a&gt;\n\nStreet Fighter Assassins Fist 2014 DVDRip x264 AC3-MiLLENiUM\n\nAuto IMDB: &lt;a href=&quot;\nhttp://www.imdb.com/title/tt3069212/&quot; rel=&quot;nofollow&quot; target=&quot;_NEW&quot;&gt;\nhttp://www.imdb.com/title/tt3069212/&lt;/a&gt;\n\n-----------------------------------------\nScreens : &lt;a href=&quot;\nhttp://i.imgur.com/haauk67.png&quot; rel=&quot;nofollow&quot; target=&quot;_NEW&quot;&gt;\nhttp://i.imgur.com/haauk67.png&lt;/a&gt; &lt;a href=&quot;\nhttp://i.imgur.com/AOxfPD0.png&quot; rel=&quot;nofollow&quot; target=&quot;_NEW&quot;&gt;\nhttp://i.imgur.com/AOxfPD0.png&lt;/a&gt; &lt;a href=&quot;\nhttp://i.imgur.com/8ztFrSs.png&quot; rel=&quot;nofollow&quot; target=&quot;_NEW&quot;&gt;\nhttp://i.imgur.com/8ztFrSs.png&lt;/a&gt; &lt;a href=&quot;\nhttp://i.imgur.com/fz5hrDH.png&quot; rel=&quot;nofollow&quot; target=&quot;_NEW&quot;&gt;\nhttp://i.imgur.com/fz5hrDH.png&lt;/a&gt; &lt;a href=&quot;\nhttp://i.imgur.com/uQzp1ZK.png&quot; rel=&quot;nofollow&quot; target=&quot;_NEW&quot;&gt;\nhttp://i.imgur.com/uQzp1ZK.png&lt;/a&gt; &lt;a href=&quot;\nhttp://i.imgur.com/PHSlR5Q.png&quot; rel=&quot;nofollow&quot; target=&quot;_NEW&quot;&gt;\nhttp://i.imgur.com/PHSlR5Q.png&lt;/a&gt;\n\n-----------------------------------------\nAuto Media Info :\nVideo Format........: AVC\nCodec ID............: V_MPEG4/ISO/AVC\nLength..............: 2h26mn\nVideo...............: 720x304 ( 25.000fps )\nBitrate.............: Variable\nAudio Format........: AC-3\nCodec ID............: A_AC3\nBit rate mode.......: Constant\nBitrate.............: 448Kbps\nChannel(s)..........: 6 channels\n\n","torrent":{"xt":"urn:btih:3f58645ce91181bdcf81552b008104154e8c1e7d","amp;dn":"Street+Fighter+Assassins+Fist+2014+DVDRip+x264+AC3-MiLLENiUM","amp;tr":["udp%3A%2F%2Ftracker.openbittorrent.com%3A80","udp%3A%2F%2Fopen.demonii.com%3A1337","udp%3A%2F%2Ftracker.coppersurfer.tk%3A6969","udp%3A%2F%2Fexodus.desync.com%3A6969"],"infoHash":"3f58645ce91181bdcf81552b008104154e8c1e7d","infoHashBuffer":{"type":"Buffer","data":[63,88,100,92,233,17,129,189,207,129,85,43,0,129,4,21,78,140,30,125]},"announce":[],"urlList":[]}}