{"title":"Nadine (New Blonde Slut Nadine First Anal &amp; DP With 2 Guys)","uid":11971662,"size":864722101,"categoryP":"porn","categoryS":"movie_clips","magnet":"?xt=urn:btih:4f8f51c8ea17efd6e8d7611db31526c610ba1040&amp;dn=Nadine+%28New+Blonde+Slut+Nadine+First+Anal+%26amp%3B+DP+With+2+Guys%29&amp;tr=udp%3A%2F%2Ftracker.openbittorrent.com%3A80&amp;tr=udp%3A%2F%2Fopen.demonii.com%3A1337&amp;tr=udp%3A%2F%2Ftracker.coppersurfer.tk%3A6969&amp;tr=udp%3A%2F%2Fexodus.desync.com%3A6969","seeders":0,"leechers":1,"uploader":"Programsmith","files":1,"time":1432851352,"description":"Gallery and Description:\n\n &lt;a href=&quot;\nhttp://imageview.me/viewerr.php?file=nebz0c10xa.jpg&quot; rel=&quot;nofollow&quot; target=&quot;_NEW&quot;&gt;\nhttp://imageview.me/viewerr.php?file=nebz0c10xa.jpg&lt;/a&gt;\n &lt;a href=&quot;\nhttp://imageview.me/viewerr.php?file=ohtauv9upo.jpg&quot; rel=&quot;nofollow&quot; target=&quot;_NEW&quot;&gt;\nhttp://imageview.me/viewerr.php?file=ohtauv9upo.jpg&lt;/a&gt;\n\nYear production: 2015\nGenre: Anal, Blonde, Blowjob, DP, Gonzo, First Gape, Facial, Hardcore\n\n\nVideo quality: SD\nVideo format: MP4\nVideo: MPEG4 Video (H264), 848x480, 50fps, 2473kbps\nAudio: AAC, 44100Hz, 2 channels, 121kbps","torrent":{"xt":"urn:btih:4f8f51c8ea17efd6e8d7611db31526c610ba1040","amp;dn":"Nadine+%28New+Blonde+Slut+Nadine+First+Anal+%26amp%3B+DP+With+2+Guys%29","amp;tr":["udp%3A%2F%2Ftracker.openbittorrent.com%3A80","udp%3A%2F%2Fopen.demonii.com%3A1337","udp%3A%2F%2Ftracker.coppersurfer.tk%3A6969","udp%3A%2F%2Fexodus.desync.com%3A6969"],"infoHash":"4f8f51c8ea17efd6e8d7611db31526c610ba1040","infoHashBuffer":{"type":"Buffer","data":[79,143,81,200,234,23,239,214,232,215,97,29,179,21,38,198,16,186,16,64]},"announce":[],"urlList":[]}}