{"title":"[FootsieBabes] Alison Tyler (Training with Allison / 22491 / 05.","uid":11962544,"size":617255422,"categoryP":"porn","categoryS":"movies","magnet":"?xt=urn:btih:5728b178141ff9d561e6e7f92c882048734cfc43&amp;dn=%5BFootsieBabes%5D+Alison+Tyler+%28Training+with+Allison+%2F+22491+%2F+05.&amp;tr=udp%3A%2F%2Ftracker.openbittorrent.com%3A80&amp;tr=udp%3A%2F%2Fopen.demonii.com%3A1337&amp;tr=udp%3A%2F%2Ftracker.coppersurfer.tk%3A6969&amp;tr=udp%3A%2F%2Fexodus.desync.com%3A6969","seeders":0,"leechers":1,"uploader":"bittuboss","files":1,"time":1432587359,"description":"ScReenS...\n\n &lt;a href=&quot;\nhttp://imgextra.biz/img-5563712c59e4a.html&quot; rel=&quot;nofollow&quot; target=&quot;_NEW&quot;&gt;\nhttp://imgextra.biz/img-5563712c59e4a.html&lt;/a&gt;\n &lt;a href=&quot;\nhttp://imgextra.biz/img-5563712d75242.html&quot; rel=&quot;nofollow&quot; target=&quot;_NEW&quot;&gt;\nhttp://imgextra.biz/img-5563712d75242.html&lt;/a&gt;","torrent":{"xt":"urn:btih:5728b178141ff9d561e6e7f92c882048734cfc43","amp;dn":"%5BFootsieBabes%5D+Alison+Tyler+%28Training+with+Allison+%2F+22491+%2F+05.","amp;tr":["udp%3A%2F%2Ftracker.openbittorrent.com%3A80","udp%3A%2F%2Fopen.demonii.com%3A1337","udp%3A%2F%2Ftracker.coppersurfer.tk%3A6969","udp%3A%2F%2Fexodus.desync.com%3A6969"],"infoHash":"5728b178141ff9d561e6e7f92c882048734cfc43","infoHashBuffer":{"type":"Buffer","data":[87,40,177,120,20,31,249,213,97,230,231,249,44,136,32,72,115,76,252,67]},"announce":[],"urlList":[]}}