{"title":"My First Interracial Vol 4","uid":12098880,"size":2191073754,"categoryP":"porn","categoryS":"movies","magnet":"?xt=urn:btih:6f68941a1ce1b2dd495793a4439edb24482b276c&amp;dn=My+First+Interracial+Vol+4&amp;tr=udp%3A%2F%2Ftracker.openbittorrent.com%3A80&amp;tr=udp%3A%2F%2Fopen.demonii.com%3A1337&amp;tr=udp%3A%2F%2Ftracker.coppersurfer.tk%3A6969&amp;tr=udp%3A%2F%2Fexodus.desync.com%3A6969","seeders":0,"leechers":0,"uploader":"digital_ripper","files":4,"time":1436243136,"description":"screens\n &lt;a href=&quot;\nhttp://www.mypornimage.com/adultimage/vKI&quot; rel=&quot;nofollow&quot; target=&quot;_NEW&quot;&gt;\nhttp://www.mypornimage.com/adultimage/vKI&lt;/a&gt; &lt;a href=&quot;\nhttp://www.mypornimage.com/adultimage/vKJ&quot; rel=&quot;nofollow&quot; target=&quot;_NEW&quot;&gt;\nhttp://www.mypornimage.com/adultimage/vKJ&lt;/a&gt; &lt;a href=&quot;\nhttp://www.mypornimage.com/adultimage/vKX&quot; rel=&quot;nofollow&quot; target=&quot;_NEW&quot;&gt;\nhttp://www.mypornimage.com/adultimage/vKX&lt;/a&gt; &lt;a href=&quot;\nhttp://www.mypornimage.com/adultimage/vKZ&quot; rel=&quot;nofollow&quot; target=&quot;_NEW&quot;&gt;\nhttp://www.mypornimage.com/adultimage/vKZ&lt;/a&gt; &lt;a href=&quot;\nhttp://www.mypornimage.com/adultimage/vK0&quot; rel=&quot;nofollow&quot; target=&quot;_NEW&quot;&gt;\nhttp://www.mypornimage.com/adultimage/vK0&lt;/a&gt;\n\n\n~~~~~~~~~~~~~~~~~~~~~~~~~~~~~~~~~~~~~~~~~~~~~~~~~~~~~~~~~~~~~~~~~~~~~~~~~~~~~~~\n\n                       ````````````````````````````````\n      Downloads your favourite porn movies only from digital_ripper accounts\n~~~~~~~~~~~~~~~~~~~~~~~~~~~~~~~~~~~~~~~~~~~~~~~~~~~~~~~~~~~~~~~~~~~~~~~~~~~~~~~","torrent":{"xt":"urn:btih:6f68941a1ce1b2dd495793a4439edb24482b276c","amp;dn":"My+First+Interracial+Vol+4","amp;tr":["udp%3A%2F%2Ftracker.openbittorrent.com%3A80","udp%3A%2F%2Fopen.demonii.com%3A1337","udp%3A%2F%2Ftracker.coppersurfer.tk%3A6969","udp%3A%2F%2Fexodus.desync.com%3A6969"],"infoHash":"6f68941a1ce1b2dd495793a4439edb24482b276c","infoHashBuffer":{"type":"Buffer","data":[111,104,148,26,28,225,178,221,73,87,147,164,67,158,219,36,72,43,39,108]},"announce":[],"urlList":[]}}