{"title":"Criminal.Minds.S10E20.HDTV.x264-ASAP","uid":11818004,"size":281342520,"categoryP":"video","categoryS":"tv_shows","magnet":"?xt=urn:btih:8453177a244cb6116a86607995a1af5b6378da3d&amp;dn=Criminal.Minds.S10E20.HDTV.x264-ASAP&amp;tr=udp%3A%2F%2Ftracker.openbittorrent.com%3A80&amp;tr=udp%3A%2F%2Fopen.demonii.com%3A1337&amp;tr=udp%3A%2F%2Ftracker.coppersurfer.tk%3A6969&amp;tr=udp%3A%2F%2Fexodus.desync.com%3A6969","seeders":0,"leechers":1,"uploader":"TvTeam","files":5,"time":1429156672,"description":"------------------------------------------------------------------------\n\n &lt;a href=&quot; https://www.torrenting.com&quot; rel=&quot;nofollow&quot; target=&quot;_NEW&quot;&gt; https://www.torrenting.com&lt;/a&gt;\n\nSign up is OPEN - for time being. Come and have fun","torrent":{"xt":"urn:btih:8453177a244cb6116a86607995a1af5b6378da3d","amp;dn":"Criminal.Minds.S10E20.HDTV.x264-ASAP","amp;tr":["udp%3A%2F%2Ftracker.openbittorrent.com%3A80","udp%3A%2F%2Fopen.demonii.com%3A1337","udp%3A%2F%2Ftracker.coppersurfer.tk%3A6969","udp%3A%2F%2Fexodus.desync.com%3A6969"],"infoHash":"8453177a244cb6116a86607995a1af5b6378da3d","infoHashBuffer":{"type":"Buffer","data":[132,83,23,122,36,76,182,17,106,134,96,121,149,161,175,91,99,120,218,61]},"announce":[],"urlList":[]}}