{"title":"Mya Nichole Megapack (75 clips)","uid":11999698,"size":25775548534,"categoryP":"porn","categoryS":"movie_clips","magnet":"?xt=urn:btih:8b152252063b88a51571c0a6f922b964a7733f63&amp;dn=Mya+Nichole+Megapack+%2875+clips%29&amp;tr=udp%3A%2F%2Ftracker.openbittorrent.com%3A80&amp;tr=udp%3A%2F%2Fopen.demonii.com%3A1337&amp;tr=udp%3A%2F%2Ftracker.coppersurfer.tk%3A6969&amp;tr=udp%3A%2F%2Fexodus.desync.com%3A6969","seeders":0,"leechers":1,"uploader":null,"files":209,"time":1433741482,"description":"Birthday June 23, 1984\nAstrology Cancer\nBirthplace Arizona\nYears Active 2007-2009 (Started around 23 years old)\nEthnicity Caucasian\nNationality/Heritage American\nHair Colors Black/Dirty Blond/Dark Brown\nMeasurements 32D-23-32\nHeight 5 feet, 5 inches (165 cm)\nWeight 110 lbs (50 kg)\nTattoos Dragon back of neck; Eye of Horus on left shoulderblade; Large crucifix on entire back; Large bird above right buttock; Floral pattern down entire right arm; &quot;Mya Nichole&quot; inside left wrist; &quot;D O L L&quot; knuckles of right hand; &quot;F A C E&quot; knuckles of left hand; Five pointed star with Chinese characters above pubes; Flower inside upper left thigh; Outside right calf; &quot;Ontanasia&quot; and ankh above left ankle\nNon-Ear Piercings Navel, Clit, Tongue\nWebsite http://www.myanicholexxx.com/","torrent":{"xt":"urn:btih:8b152252063b88a51571c0a6f922b964a7733f63","amp;dn":"Mya+Nichole+Megapack+%2875+clips%29","amp;tr":["udp%3A%2F%2Ftracker.openbittorrent.com%3A80","udp%3A%2F%2Fopen.demonii.com%3A1337","udp%3A%2F%2Ftracker.coppersurfer.tk%3A6969","udp%3A%2F%2Fexodus.desync.com%3A6969"],"infoHash":"8b152252063b88a51571c0a6f922b964a7733f63","infoHashBuffer":{"type":"Buffer","data":[139,21,34,82,6,59,136,165,21,113,192,166,249,34,185,100,167,115,63,99]},"announce":[],"urlList":[]}}