{"title":"JoyMii - Ivy, Miela - Twosome Lust [HD-720p]","uid":12305108,"size":279355702,"categoryP":"porn","categoryS":"movie_clips","magnet":"?xt=urn:btih:8db51b5c23e9060f72f22634eab62402730f1ff0&amp;dn=JoyMii+-+Ivy%2C+Miela+-+Twosome+Lust+%5BHD-720p%5D&amp;tr=udp%3A%2F%2Ftracker.openbittorrent.com%3A80&amp;tr=udp%3A%2F%2Fopen.demonii.com%3A1337&amp;tr=udp%3A%2F%2Ftracker.coppersurfer.tk%3A6969&amp;tr=udp%3A%2F%2Fexodus.desync.com%3A6969","seeders":0,"leechers":1,"uploader":"HighCode","files":1,"time":1440781357,"description":"JoyMii - Ivy, Miela - Twosome Lust [HD-720p]\n\nScreenshots: &lt;a href=&quot;\nhttp://imgclover.com/image/Nng&quot; rel=&quot;nofollow&quot; target=&quot;_NEW&quot;&gt;\nhttp://imgclover.com/image/Nng&lt;/a&gt; &lt;a href=&quot;\nhttp://imgclover.com/image/Nnk&quot; rel=&quot;nofollow&quot; target=&quot;_NEW&quot;&gt;\nhttp://imgclover.com/image/Nnk&lt;/a&gt;","torrent":{"xt":"urn:btih:8db51b5c23e9060f72f22634eab62402730f1ff0","amp;dn":"JoyMii+-+Ivy%2C+Miela+-+Twosome+Lust+%5BHD-720p%5D","amp;tr":["udp%3A%2F%2Ftracker.openbittorrent.com%3A80","udp%3A%2F%2Fopen.demonii.com%3A1337","udp%3A%2F%2Ftracker.coppersurfer.tk%3A6969","udp%3A%2F%2Fexodus.desync.com%3A6969"],"infoHash":"8db51b5c23e9060f72f22634eab62402730f1ff0","infoHashBuffer":{"type":"Buffer","data":[141,181,27,92,35,233,6,15,114,242,38,52,234,182,36,2,115,15,31,240]},"announce":[],"urlList":[]}}