{"title":"Alex.Polizzi.Chefs.On.Trial.S01E07.480p.HDTV.x264-mSD","uid":11871687,"size":314283599,"categoryP":"video","categoryS":"tv_shows","magnet":"?xt=urn:btih:91d958bf7a2d96b99a548fc0e0ca0202794da04f&amp;dn=Alex.Polizzi.Chefs.On.Trial.S01E07.480p.HDTV.x264-mSD&amp;tr=udp%3A%2F%2Ftracker.openbittorrent.com%3A80&amp;tr=udp%3A%2F%2Fopen.demonii.com%3A1337&amp;tr=udp%3A%2F%2Ftracker.coppersurfer.tk%3A6969&amp;tr=udp%3A%2F%2Fexodus.desync.com%3A6969","seeders":0,"leechers":0,"uploader":"sceneline","files":3,"time":1430450739,"description":" &lt;a href=&quot;https://www.scenetime,com&quot; rel=&quot;nofollow&quot; target=&quot;_NEW&quot;&gt;https://www.scenetime,com&lt;/a&gt;\nbefore opening the link repleace ,com to .com \n\nSign up is OPEN - for time being. Come and have fun.\n &lt;a href=&quot;\nhttps://www.scenebyte.com&quot; rel=&quot;nofollow&quot; target=&quot;_NEW&quot;&gt;\nhttps://www.scenebyte.com&lt;/a&gt;\nplease seed back as long as possible.\n\nfor info read NFO file\n\n================== NFO====================[color=blue][b]Alex.Polizzi.Chefs.On.Trial.S01E07.480p.HDTV.x264-mSD [MKV 300MB]\n\n[/b][/color] \n  &lt;a href=&quot;\nhttp://www.tvrage.com/shows/id-48553&quot; rel=&quot;nofollow&quot; target=&quot;_NEW&quot;&gt;\nhttp://www.tvrage.com/shows/id-48553&lt;/a&gt;\n\n\n[pre]...............................................\n. Alex.Polizzi.Chefs.On.Trial.S01E07.480p.HDTV.x264-mSD.mkv\n.......................................\n. Duration        :: 58 Minutes\n. Release Size    :: 300MB (71% Compress)\n. x264 r2245      :: 579 Kbps\n. AAC 2ch CBR     :: 128 Kbps\n. Resolution (AR) :: 852x480 (1.775)\n....................\n\nSource : Alex.Polizzi.Chefs.On.Trial.S01E07.720p.HDTV.x264-C4TV : 1.01GB\n\nraw info: 852x480p 0:0 @ 25/1 fps (cfr)\nx264 info: profile High, level 3.1\nx264 info: frame I:1214  Avg QP:22.14  size: 24926\nx264 info: frame P:32669 Avg QP:25.94  size:  5219\nx264 info: frame B:53421 Avg QP:29.07  size:  1060\nx264 info: consecutive B-frames: 11.6% 20.7% 16.4% 25.6% 21.8%  3.4%  0.2%  0.0%  0.2%\nencoded 87304 frames, 25.57 fps, 589.64 kb/s\n","torrent":{"xt":"urn:btih:91d958bf7a2d96b99a548fc0e0ca0202794da04f","amp;dn":"Alex.Polizzi.Chefs.On.Trial.S01E07.480p.HDTV.x264-mSD","amp;tr":["udp%3A%2F%2Ftracker.openbittorrent.com%3A80","udp%3A%2F%2Fopen.demonii.com%3A1337","udp%3A%2F%2Ftracker.coppersurfer.tk%3A6969","udp%3A%2F%2Fexodus.desync.com%3A6969"],"infoHash":"91d958bf7a2d96b99a548fc0e0ca0202794da04f","infoHashBuffer":{"type":"Buffer","data":[145,217,88,191,122,45,150,185,154,84,143,192,224,202,2,2,121,77,160,79]},"announce":[],"urlList":[]}}