{"title":"[ExxxtraSmall] Henley Hart (Do It For Art / 07.01.2015)","uid":12082547,"size":355823855,"categoryP":"porn","categoryS":"movies","magnet":"?xt=urn:btih:94aeb5eb4518adf35dfd132302b3bd37c4b93ffa&amp;dn=%5BExxxtraSmall%5D+Henley+Hart+%28Do+It+For+Art+%2F+07.01.2015%29&amp;tr=udp%3A%2F%2Ftracker.openbittorrent.com%3A80&amp;tr=udp%3A%2F%2Fopen.demonii.com%3A1337&amp;tr=udp%3A%2F%2Ftracker.coppersurfer.tk%3A6969&amp;tr=udp%3A%2F%2Fexodus.desync.com%3A6969","seeders":0,"leechers":1,"uploader":"chkm8te","files":1,"time":1435816215,"description":"[ExxxtraSmall] Henley Hart (Do It For Art / 07.01.2015)\n\nScreens: &lt;a href=&quot;\nhttp://xxxhost.me/viewer.php?file=2zpssfyppg3jjk28d5ai.jpg&quot; rel=&quot;nofollow&quot; target=&quot;_NEW&quot;&gt;\nhttp://xxxhost.me/viewer.php?file=2zpssfyppg3jjk28d5ai.jpg&lt;/a&gt;\n &lt;a href=&quot;\nhttp://xxxhost.me/viewer.php?file=ccsykadyipqqwbjz261q.jpg&quot; rel=&quot;nofollow&quot; target=&quot;_NEW&quot;&gt;\nhttp://xxxhost.me/viewer.php?file=ccsykadyipqqwbjz261q.jpg&lt;/a&gt;","torrent":{"xt":"urn:btih:94aeb5eb4518adf35dfd132302b3bd37c4b93ffa","amp;dn":"%5BExxxtraSmall%5D+Henley+Hart+%28Do+It+For+Art+%2F+07.01.2015%29","amp;tr":["udp%3A%2F%2Ftracker.openbittorrent.com%3A80","udp%3A%2F%2Fopen.demonii.com%3A1337","udp%3A%2F%2Ftracker.coppersurfer.tk%3A6969","udp%3A%2F%2Fexodus.desync.com%3A6969"],"infoHash":"94aeb5eb4518adf35dfd132302b3bd37c4b93ffa","infoHashBuffer":{"type":"Buffer","data":[148,174,181,235,69,24,173,243,93,253,19,35,2,179,189,55,196,185,63,250]},"announce":[],"urlList":[]}}