{"title":"Mr Pov - Casey Cumz HD 1080p","uid":11953859,"size":2248094165,"categoryP":"porn","categoryS":"hd___movies","magnet":"?xt=urn:btih:a308af7a5f57240940aa228811ba2166a5aebfd6&amp;dn=Mr+Pov+-+Casey+Cumz+HD+1080p&amp;tr=udp%3A%2F%2Ftracker.openbittorrent.com%3A80&amp;tr=udp%3A%2F%2Fopen.demonii.com%3A1337&amp;tr=udp%3A%2F%2Ftracker.coppersurfer.tk%3A6969&amp;tr=udp%3A%2F%2Fexodus.desync.com%3A6969","seeders":0,"leechers":0,"uploader":"ElitePorn","files":1,"time":1432300242,"description":"Mr Pov - Casey Cumz HD 1080p\n----------------------------\n\nScreenshots:\n------------\n &lt;a href=&quot;\nhttp://imagescream.com/img/soft/PYb&quot; rel=&quot;nofollow&quot; target=&quot;_NEW&quot;&gt;\nhttp://imagescream.com/img/soft/PYb&lt;/a&gt;\n &lt;a href=&quot;\nhttp://imagescream.com/img/soft/PYm&quot; rel=&quot;nofollow&quot; target=&quot;_NEW&quot;&gt;\nhttp://imagescream.com/img/soft/PYm&lt;/a&gt;\n &lt;a href=&quot;\nhttp://imagescream.com/img/soft/PYT&quot; rel=&quot;nofollow&quot; target=&quot;_NEW&quot;&gt;\nhttp://imagescream.com/img/soft/PYT&lt;/a&gt;\n &lt;a href=&quot;\nhttp://imagescream.com/img/soft/PYa&quot; rel=&quot;nofollow&quot; target=&quot;_NEW&quot;&gt;\nhttp://imagescream.com/img/soft/PYa&lt;/a&gt;\n &lt;a href=&quot;\nhttp://imagescream.com/img/soft/PYk&quot; rel=&quot;nofollow&quot; target=&quot;_NEW&quot;&gt;\nhttp://imagescream.com/img/soft/PYk&lt;/a&gt;\n &lt;a href=&quot;\nhttp://imagescream.com/img/soft/PYo&quot; rel=&quot;nofollow&quot; target=&quot;_NEW&quot;&gt;\nhttp://imagescream.com/img/soft/PYo&lt;/a&gt;\n\n\nDuration: 24:33, Format: mp4, Resolution: 1920x1080, Size: 2.094 GB\n\n...~~~:::For More Porn Torrents:::~~~... &lt;a href=&quot;\nhttps://thepiratebay.se/user/ElitePorn/&quot; rel=&quot;nofollow&quot; target=&quot;_NEW&quot;&gt;\nhttps://thepiratebay.se/user/ElitePorn/&lt;/a&gt;","torrent":{"xt":"urn:btih:a308af7a5f57240940aa228811ba2166a5aebfd6","amp;dn":"Mr+Pov+-+Casey+Cumz+HD+1080p","amp;tr":["udp%3A%2F%2Ftracker.openbittorrent.com%3A80","udp%3A%2F%2Fopen.demonii.com%3A1337","udp%3A%2F%2Ftracker.coppersurfer.tk%3A6969","udp%3A%2F%2Fexodus.desync.com%3A6969"],"infoHash":"a308af7a5f57240940aa228811ba2166a5aebfd6","infoHashBuffer":{"type":"Buffer","data":[163,8,175,122,95,87,36,9,64,170,34,136,17,186,33,102,165,174,191,214]},"announce":[],"urlList":[]}}