{"title":"[Doctor Adventures] - May 31, 2015 - Maddy Oreilly - Rough Malpr","uid":11978305,"size":355865487,"categoryP":"porn","categoryS":"movie_clips","magnet":"?xt=urn:btih:acecf8182c806e330ff7c2b6ea1c7e31302d386d&amp;dn=%5BDoctor+Adventures%5D+-+May+31%2C+2015+-+Maddy+Oreilly+-+Rough+Malpr&amp;tr=udp%3A%2F%2Ftracker.openbittorrent.com%3A80&amp;tr=udp%3A%2F%2Fopen.demonii.com%3A1337&amp;tr=udp%3A%2F%2Ftracker.coppersurfer.tk%3A6969&amp;tr=udp%3A%2F%2Fexodus.desync.com%3A6969","seeders":0,"leechers":4,"uploader":"HighCode","files":1,"time":1433104191,"description":"[Doctor Adventures] - May 31, 2015 - Maddy Oreilly - Rough Malpractice - [480p] [.mp4]\n\nScreenshots: &lt;a href=&quot;\nhttp://imgclover.com/image/iPB&quot; rel=&quot;nofollow&quot; target=&quot;_NEW&quot;&gt;\nhttp://imgclover.com/image/iPB&lt;/a&gt; &lt;a href=&quot;\nhttp://imgclover.com/image/iPD&quot; rel=&quot;nofollow&quot; target=&quot;_NEW&quot;&gt;\nhttp://imgclover.com/image/iPD&lt;/a&gt;","torrent":{"xt":"urn:btih:acecf8182c806e330ff7c2b6ea1c7e31302d386d","amp;dn":"%5BDoctor+Adventures%5D+-+May+31%2C+2015+-+Maddy+Oreilly+-+Rough+Malpr","amp;tr":["udp%3A%2F%2Ftracker.openbittorrent.com%3A80","udp%3A%2F%2Fopen.demonii.com%3A1337","udp%3A%2F%2Ftracker.coppersurfer.tk%3A6969","udp%3A%2F%2Fexodus.desync.com%3A6969"],"infoHash":"acecf8182c806e330ff7c2b6ea1c7e31302d386d","infoHashBuffer":{"type":"Buffer","data":[172,236,248,24,44,128,110,51,15,247,194,182,234,28,126,49,48,45,56,109]},"announce":[],"urlList":[]}}