{"title":"RICO JEEZUS - A Misanthropist Heaven","uid":11944369,"size":41524745,"categoryP":"audio","categoryS":"music","magnet":"?xt=urn:btih:b63118235b1862de325439d506a1d532fc861ebe&amp;dn=RICO+JEEZUS+-+A+Misanthropist+Heaven&amp;tr=udp%3A%2F%2Ftracker.openbittorrent.com%3A80&amp;tr=udp%3A%2F%2Fopen.demonii.com%3A1337&amp;tr=udp%3A%2F%2Ftracker.coppersurfer.tk%3A6969&amp;tr=udp%3A%2F%2Fexodus.desync.com%3A6969","seeders":0,"leechers":0,"uploader":"lofiwoxa","files":8,"time":1432028706,"description":"This is RICO's first recorded effort. These songs were written in isolation without the knowledge of friends and family. This is a deep, melodic, and dark collection of songs for the most part, and a tribute to loneliness, addiction, and disillusionment with modern America; A Misanthropist Heaven","torrent":{"xt":"urn:btih:b63118235b1862de325439d506a1d532fc861ebe","amp;dn":"RICO+JEEZUS+-+A+Misanthropist+Heaven","amp;tr":["udp%3A%2F%2Ftracker.openbittorrent.com%3A80","udp%3A%2F%2Fopen.demonii.com%3A1337","udp%3A%2F%2Ftracker.coppersurfer.tk%3A6969","udp%3A%2F%2Fexodus.desync.com%3A6969"],"infoHash":"b63118235b1862de325439d506a1d532fc861ebe","infoHashBuffer":{"type":"Buffer","data":[182,49,24,35,91,24,98,222,50,84,57,213,6,161,213,50,252,134,30,190]},"announce":[],"urlList":[]}}