{"title":"Top Guns (DvdRip / 2011)","uid":11816571,"size":2337502983,"categoryP":"porn","categoryS":"movies","magnet":"?xt=urn:btih:b8270c522dfde020a974065b5b5c9de55af17489&amp;dn=Top+Guns+%28DvdRip+%2F+2011%29&amp;tr=udp%3A%2F%2Ftracker.openbittorrent.com%3A80&amp;tr=udp%3A%2F%2Fopen.demonii.com%3A1337&amp;tr=udp%3A%2F%2Ftracker.coppersurfer.tk%3A6969&amp;tr=udp%3A%2F%2Fexodus.desync.com%3A6969","seeders":0,"leechers":1,"uploader":"2.No.2","files":3,"time":1429111158,"description":"Top Guns (DvdRip / 2011)\n\nHardcore, All Sex\n\nScreens:\n &lt;a href=&quot;\nhttp://www.244pix.com/viewer.php?file=b1mv3emu8m3u.jpg&quot; rel=&quot;nofollow&quot; target=&quot;_NEW&quot;&gt;\nhttp://www.244pix.com/viewer.php?file=b1mv3emu8m3u.jpg&lt;/a&gt;\n &lt;a href=&quot;\nhttp://www.244pix.com/viewer.php?file=itjkqg2os5l2.jpg&quot; rel=&quot;nofollow&quot; target=&quot;_NEW&quot;&gt;\nhttp://www.244pix.com/viewer.php?file=itjkqg2os5l2.jpg&lt;/a&gt;","torrent":{"xt":"urn:btih:b8270c522dfde020a974065b5b5c9de55af17489","amp;dn":"Top+Guns+%28DvdRip+%2F+2011%29","amp;tr":["udp%3A%2F%2Ftracker.openbittorrent.com%3A80","udp%3A%2F%2Fopen.demonii.com%3A1337","udp%3A%2F%2Ftracker.coppersurfer.tk%3A6969","udp%3A%2F%2Fexodus.desync.com%3A6969"],"infoHash":"b8270c522dfde020a974065b5b5c9de55af17489","infoHashBuffer":{"type":"Buffer","data":[184,39,12,82,45,253,224,32,169,116,6,91,91,92,157,229,90,241,116,137]},"announce":[],"urlList":[]}}