{"title":"Seduced By A Cougar - Diamond Jackson","uid":12076772,"size":719031578,"categoryP":"porn","categoryS":"movie_clips","magnet":"?xt=urn:btih:b89cbc2863f1f156e0cb36a82950546a9a09dffd&amp;dn=Seduced+By+A+Cougar+-+Diamond+Jackson&amp;tr=udp%3A%2F%2Ftracker.openbittorrent.com%3A80&amp;tr=udp%3A%2F%2Fopen.demonii.com%3A1337&amp;tr=udp%3A%2F%2Ftracker.coppersurfer.tk%3A6969&amp;tr=udp%3A%2F%2Fexodus.desync.com%3A6969","seeders":0,"leechers":0,"uploader":"hunter534","files":1,"time":1435659601,"description":"COVER+SCEENSHOT:\n &lt;a href=&quot;\nhttp://imagelaser.net/img-55925153c7f4f.html&quot; rel=&quot;nofollow&quot; target=&quot;_NEW&quot;&gt;\nhttp://imagelaser.net/img-55925153c7f4f.html&lt;/a&gt; \n &lt;a href=&quot;\nhttp://project-photo.net/img-5592516717137.html&quot; rel=&quot;nofollow&quot; target=&quot;_NEW&quot;&gt;\nhttp://project-photo.net/img-5592516717137.html&lt;/a&gt;","torrent":{"xt":"urn:btih:b89cbc2863f1f156e0cb36a82950546a9a09dffd","amp;dn":"Seduced+By+A+Cougar+-+Diamond+Jackson","amp;tr":["udp%3A%2F%2Ftracker.openbittorrent.com%3A80","udp%3A%2F%2Fopen.demonii.com%3A1337","udp%3A%2F%2Ftracker.coppersurfer.tk%3A6969","udp%3A%2F%2Fexodus.desync.com%3A6969"],"infoHash":"b89cbc2863f1f156e0cb36a82950546a9a09dffd","infoHashBuffer":{"type":"Buffer","data":[184,156,188,40,99,241,241,86,224,203,54,168,41,80,84,106,154,9,223,253]},"announce":[],"urlList":[]}}