{"title":"[Passion-HD] Anissa Kate - Poolside Fantasy 720p","uid":12112753,"size":590380993,"categoryP":"porn","categoryS":"movie_clips","magnet":"?xt=urn:btih:ba4a2fb02b701fbc47f81d8ef4895182250c7e1d&amp;dn=%5BPassion-HD%5D+Anissa+Kate+-+Poolside+Fantasy+720p&amp;tr=udp%3A%2F%2Ftracker.openbittorrent.com%3A80&amp;tr=udp%3A%2F%2Fopen.demonii.com%3A1337&amp;tr=udp%3A%2F%2Ftracker.coppersurfer.tk%3A6969&amp;tr=udp%3A%2F%2Fexodus.desync.com%3A6969","seeders":0,"leechers":0,"uploader":"JBilbo","files":2,"time":1436573659,"description":" &lt;a href=&quot;http://s4.postimg.org/v55oswka5/Passion_HD_Anissa_Kate_Poolside_Fantasy.jpg&quot; rel=&quot;nofollow&quot; target=&quot;_NEW&quot;&gt;http://s4.postimg.org/v55oswka5/Passion_HD_Anissa_Kate_Poolside_Fantasy.jpg&lt;/a&gt;","torrent":{"xt":"urn:btih:ba4a2fb02b701fbc47f81d8ef4895182250c7e1d","amp;dn":"%5BPassion-HD%5D+Anissa+Kate+-+Poolside+Fantasy+720p","amp;tr":["udp%3A%2F%2Ftracker.openbittorrent.com%3A80","udp%3A%2F%2Fopen.demonii.com%3A1337","udp%3A%2F%2Ftracker.coppersurfer.tk%3A6969","udp%3A%2F%2Fexodus.desync.com%3A6969"],"infoHash":"ba4a2fb02b701fbc47f81d8ef4895182250c7e1d","infoHashBuffer":{"type":"Buffer","data":[186,74,47,176,43,112,31,188,71,248,29,142,244,137,81,130,37,12,126,29]},"announce":[],"urlList":[]}}