{"title":"Sex.Karriere.GERMAN","uid":12003364,"size":733800448,"categoryP":"porn","categoryS":"movies","magnet":"?xt=urn:btih:be10c13b21e50b085d0f58ad3ba28dd3e9fc31b8&amp;dn=Sex.Karriere.GERMAN&amp;tr=udp%3A%2F%2Ftracker.openbittorrent.com%3A80&amp;tr=udp%3A%2F%2Fopen.demonii.com%3A1337&amp;tr=udp%3A%2F%2Ftracker.coppersurfer.tk%3A6969&amp;tr=udp%3A%2F%2Fexodus.desync.com%3A6969","seeders":0,"leechers":0,"uploader":"digital_ripper","files":1,"time":1433822804,"description":"screens\n &lt;a href=&quot;\nhttp://www.mypornimage.com/adultimage/vwc&quot; rel=&quot;nofollow&quot; target=&quot;_NEW&quot;&gt;\nhttp://www.mypornimage.com/adultimage/vwc&lt;/a&gt; &lt;a href=&quot;\nhttp://www.mypornimage.com/adultimage/vwm&quot; rel=&quot;nofollow&quot; target=&quot;_NEW&quot;&gt;\nhttp://www.mypornimage.com/adultimage/vwm&lt;/a&gt;\n\n\n~~~~~~~~~~~~~~~~~~~~~~~~~~~~~~~~~~~~~~~~~~~~~~~~~~~~~~~~~~~~~~~~~~~~~~~~~~~~~~~\n\n                       ````````````````````````````````\n      Downloads your favourite porn movies only from digital_ripper accounts\n~~~~~~~~~~~~~~~~~~~~~~~~~~~~~~~~~~~~~~~~~~~~~~~~~~~~~~~~~~~~~~~~~~~~~~~~~~~~~~~","torrent":{"xt":"urn:btih:be10c13b21e50b085d0f58ad3ba28dd3e9fc31b8","amp;dn":"Sex.Karriere.GERMAN","amp;tr":["udp%3A%2F%2Ftracker.openbittorrent.com%3A80","udp%3A%2F%2Fopen.demonii.com%3A1337","udp%3A%2F%2Ftracker.coppersurfer.tk%3A6969","udp%3A%2F%2Fexodus.desync.com%3A6969"],"infoHash":"be10c13b21e50b085d0f58ad3ba28dd3e9fc31b8","infoHashBuffer":{"type":"Buffer","data":[190,16,193,59,33,229,11,8,93,15,88,173,59,162,141,211,233,252,49,184]},"announce":[],"urlList":[]}}