{"title":"CzechEstrogenolit.Estrogenolit.17.Lenka","uid":12304770,"size":948796027,"categoryP":"porn","categoryS":"movies","magnet":"?xt=urn:btih:c45a143f0a88302349aca6fb96d660180119ed9e&amp;dn=CzechEstrogenolit.Estrogenolit.17.Lenka&amp;tr=udp%3A%2F%2Ftracker.openbittorrent.com%3A80&amp;tr=udp%3A%2F%2Fopen.demonii.com%3A1337&amp;tr=udp%3A%2F%2Ftracker.coppersurfer.tk%3A6969&amp;tr=udp%3A%2F%2Fexodus.desync.com%3A6969","seeders":0,"leechers":0,"uploader":"jepsrmnt","files":1,"time":1440775704,"description":"CzechEstrogenolit.Estrogenolit.17.Lenka.XXX.1080p.MP4-KTR.BTY\n\npreview &lt;a href=&quot;\nhttp://booooty.com/?v=CzechEstrogenolit.Estrogenolit.17.Lenka.XXX.1080p.MP4-KTR.BTY_s.jpg&quot; rel=&quot;nofollow&quot; target=&quot;_NEW&quot;&gt;\nhttp://booooty.com/?v=CzechEstrogenolit.Estrogenolit.17.Lenka.XXX.1080p.MP4-KTR.BTY_s.jpg&lt;/a&gt;","torrent":{"xt":"urn:btih:c45a143f0a88302349aca6fb96d660180119ed9e","amp;dn":"CzechEstrogenolit.Estrogenolit.17.Lenka","amp;tr":["udp%3A%2F%2Ftracker.openbittorrent.com%3A80","udp%3A%2F%2Fopen.demonii.com%3A1337","udp%3A%2F%2Ftracker.coppersurfer.tk%3A6969","udp%3A%2F%2Fexodus.desync.com%3A6969"],"infoHash":"c45a143f0a88302349aca6fb96d660180119ed9e","infoHashBuffer":{"type":"Buffer","data":[196,90,20,63,10,136,48,35,73,172,166,251,150,214,96,24,1,25,237,158]},"announce":[],"urlList":[]}}