{"title":"MyFreeCams - SxyLilith [Upstore premium]","uid":12094031,"size":5364459906,"categoryP":"porn","categoryS":"movie_clips","magnet":"?xt=urn:btih:c895d66b44dc3f1a22693cdb11e6cf31a3352f50&amp;dn=MyFreeCams+-+SxyLilith+%5BUpstore+premium%5D&amp;tr=udp%3A%2F%2Ftracker.openbittorrent.com%3A80&amp;tr=udp%3A%2F%2Fopen.demonii.com%3A1337&amp;tr=udp%3A%2F%2Ftracker.coppersurfer.tk%3A6969&amp;tr=udp%3A%2F%2Fexodus.desync.com%3A6969","seeders":0,"leechers":0,"uploader":"Ctrlme","files":135,"time":1436115766,"description":"Screenshot(s):  &lt;a href=&quot;\nhttp://imgctrl.com/image/As3&quot; rel=&quot;nofollow&quot; target=&quot;_NEW&quot;&gt;\nhttp://imgctrl.com/image/As3&lt;/a&gt; &lt;a href=&quot;\nhttp://imgctrl.com/image/AsE&quot; rel=&quot;nofollow&quot; target=&quot;_NEW&quot;&gt;\nhttp://imgctrl.com/image/AsE&lt;/a&gt; &lt;a href=&quot;\nhttp://imgctrl.com/image/AsF&quot; rel=&quot;nofollow&quot; target=&quot;_NEW&quot;&gt;\nhttp://imgctrl.com/image/AsF&lt;/a&gt; &lt;a href=&quot;\nhttp://imgctrl.com/image/AsS&quot; rel=&quot;nofollow&quot; target=&quot;_NEW&quot;&gt;\nhttp://imgctrl.com/image/AsS&lt;/a&gt; &lt;a href=&quot;\nhttp://imgctrl.com/image/Asf&quot; rel=&quot;nofollow&quot; target=&quot;_NEW&quot;&gt;\nhttp://imgctrl.com/image/Asf&lt;/a&gt; &lt;a href=&quot;\nhttp://imgctrl.com/image/Aso&quot; rel=&quot;nofollow&quot; target=&quot;_NEW&quot;&gt;\nhttp://imgctrl.com/image/Aso&lt;/a&gt; &lt;a href=&quot;\nhttp://imgctrl.com/image/As4&quot; rel=&quot;nofollow&quot; target=&quot;_NEW&quot;&gt;\nhttp://imgctrl.com/image/As4&lt;/a&gt; &lt;a href=&quot;\nhttp://imgctrl.com/image/AsJ&quot; rel=&quot;nofollow&quot; target=&quot;_NEW&quot;&gt;\nhttp://imgctrl.com/image/AsJ&lt;/a&gt; &lt;a href=&quot;\nhttp://imgctrl.com/image/AsK&quot; rel=&quot;nofollow&quot; target=&quot;_NEW&quot;&gt;\nhttp://imgctrl.com/image/AsK&lt;/a&gt; &lt;a href=&quot;\nhttp://imgctrl.com/image/Asm&quot; rel=&quot;nofollow&quot; target=&quot;_NEW&quot;&gt;\nhttp://imgctrl.com/image/Asm&lt;/a&gt; &lt;a href=&quot;\nhttp://imgctrl.com/image/Asr&quot; rel=&quot;nofollow&quot; target=&quot;_NEW&quot;&gt;\nhttp://imgctrl.com/image/Asr&lt;/a&gt; &lt;a href=&quot;\nhttp://imgctrl.com/image/Ass&quot; rel=&quot;nofollow&quot; target=&quot;_NEW&quot;&gt;\nhttp://imgctrl.com/image/Ass&lt;/a&gt; &lt;a href=&quot;\nhttp://imgctrl.com/image/As7&quot; rel=&quot;nofollow&quot; target=&quot;_NEW&quot;&gt;\nhttp://imgctrl.com/image/As7&lt;/a&gt; &lt;a href=&quot;\nhttp://imgctrl.com/image/Asu&quot; rel=&quot;nofollow&quot; target=&quot;_NEW&quot;&gt;\nhttp://imgctrl.com/image/Asu&lt;/a&gt; &lt;a href=&quot;\nhttp://imgctrl.com/image/As2&quot; rel=&quot;nofollow&quot; target=&quot;_NEW&quot;&gt;\nhttp://imgctrl.com/image/As2&lt;/a&gt; &lt;a href=&quot;\nhttp://imgctrl.com/image/AsM&quot; rel=&quot;nofollow&quot; target=&quot;_NEW&quot;&gt;\nhttp://imgctrl.com/image/AsM&lt;/a&gt; &lt;a href=&quot;\nhttp://imgctrl.com/image/As0&quot; rel=&quot;nofollow&quot; target=&quot;_NEW&quot;&gt;\nhttp://imgctrl.com/image/As0&lt;/a&gt; &lt;a href=&quot;\nhttp://imgctrl.com/image/AsH&quot; rel=&quot;nofollow&quot; target=&quot;_NEW&quot;&gt;\nhttp://imgctrl.com/image/AsH&lt;/a&gt; &lt;a href=&quot;\nhttp://imgctrl.com/image/AsZ&quot; rel=&quot;nofollow&quot; target=&quot;_NEW&quot;&gt;\nhttp://imgctrl.com/image/AsZ&lt;/a&gt; &lt;a href=&quot;\nhttp://imgctrl.com/image/Asi&quot; rel=&quot;nofollow&quot; target=&quot;_NEW&quot;&gt;\nhttp://imgctrl.com/image/Asi&lt;/a&gt; &lt;a href=&quot;\nhttp://imgctrl.com/image/Asq&quot; rel=&quot;nofollow&quot; target=&quot;_NEW&quot;&gt;\nhttp://imgctrl.com/image/Asq&lt;/a&gt; &lt;a href=&quot;\nhttp://imgctrl.com/image/Asx&quot; rel=&quot;nofollow&quot; target=&quot;_NEW&quot;&gt;\nhttp://imgctrl.com/image/Asx&lt;/a&gt; &lt;a href=&quot;\nhttp://imgctrl.com/image/As6&quot; rel=&quot;nofollow&quot; target=&quot;_NEW&quot;&gt;\nhttp://imgctrl.com/image/As6&lt;/a&gt; &lt;a href=&quot;\nhttp://imgctrl.com/image/AsB&quot; rel=&quot;nofollow&quot; target=&quot;_NEW&quot;&gt;\nhttp://imgctrl.com/image/AsB&lt;/a&gt; &lt;a href=&quot;\nhttp://imgctrl.com/image/AsI&quot; rel=&quot;nofollow&quot; target=&quot;_NEW&quot;&gt;\nhttp://imgctrl.com/image/AsI&lt;/a&gt; &lt;a href=&quot;\nhttp://imgctrl.com/image/AsL&quot; rel=&quot;nofollow&quot; target=&quot;_NEW&quot;&gt;\nhttp://imgctrl.com/image/AsL&lt;/a&gt; &lt;a href=&quot;\nhttp://imgctrl.com/image/AsU&quot; rel=&quot;nofollow&quot; target=&quot;_NEW&quot;&gt;\nhttp://imgctrl.com/image/AsU&lt;/a&gt; &lt;a href=&quot;\nhttp://imgctrl.com/image/Asg&quot; rel=&quot;nofollow&quot; target=&quot;_NEW&quot;&gt;\nhttp://imgctrl.com/image/Asg&lt;/a&gt; &lt;a href=&quot;\nhttp://imgctrl.com/image/Asj&quot; rel=&quot;nofollow&quot; target=&quot;_NEW&quot;&gt;\nhttp://imgctrl.com/image/Asj&lt;/a&gt; &lt;a href=&quot;\nhttp://imgctrl.com/image/Asn&quot; rel=&quot;nofollow&quot; target=&quot;_NEW&quot;&gt;\nhttp://imgctrl.com/image/Asn&lt;/a&gt; &lt;a href=&quot;\nhttp://imgctrl.com/image/Ast&quot; rel=&quot;nofollow&quot; target=&quot;_NEW&quot;&gt;\nhttp://imgctrl.com/image/Ast&lt;/a&gt; &lt;a href=&quot;\nhttp://imgctrl.com/image/As9&quot; rel=&quot;nofollow&quot; target=&quot;_NEW&quot;&gt;\nhttp://imgctrl.com/image/As9&lt;/a&gt; &lt;a href=&quot;\nhttp://imgctrl.com/image/Ask&quot; rel=&quot;nofollow&quot; target=&quot;_NEW&quot;&gt;\nhttp://imgctrl.com/image/Ask&lt;/a&gt; &lt;a href=&quot;\nhttp://imgctrl.com/image/Ase&quot; rel=&quot;nofollow&quot; target=&quot;_NEW&quot;&gt;\nhttp://imgctrl.com/image/Ase&lt;/a&gt; &lt;a href=&quot;\nhttp://imgctrl.com/image/Ash&quot; rel=&quot;nofollow&quot; target=&quot;_NEW&quot;&gt;\nhttp://imgctrl.com/image/Ash&lt;/a&gt; &lt;a href=&quot;\nhttp://imgctrl.com/image/As5&quot; rel=&quot;nofollow&quot; target=&quot;_NEW&quot;&gt;\nhttp://imgctrl.com/image/As5&lt;/a&gt; &lt;a href=&quot;\nhttp://imgctrl.com/image/AsR&quot; rel=&quot;nofollow&quot; target=&quot;_NEW&quot;&gt;\nhttp://imgctrl.com/image/AsR&lt;/a&gt; &lt;a href=&quot;\nhttp://imgctrl.com/image/Asc&quot; rel=&quot;nofollow&quot; target=&quot;_NEW&quot;&gt;\nhttp://imgctrl.com/image/Asc&lt;/a&gt; &lt;a href=&quot;\nhttp://imgctrl.com/image/Asd&quot; rel=&quot;nofollow&quot; target=&quot;_NEW&quot;&gt;\nhttp://imgctrl.com/image/Asd&lt;/a&gt; &lt;a href=&quot;\nhttp://imgctrl.com/image/Asw&quot; rel=&quot;nofollow&quot; target=&quot;_NEW&quot;&gt;\nhttp://imgctrl.com/image/Asw&lt;/a&gt; &lt;a href=&quot;\nhttp://imgctrl.com/image/As1&quot; rel=&quot;nofollow&quot; target=&quot;_NEW&quot;&gt;\nhttp://imgctrl.com/image/As1&lt;/a&gt; &lt;a href=&quot;\nhttp://imgctrl.com/image/AsO&quot; rel=&quot;nofollow&quot; target=&quot;_NEW&quot;&gt;\nhttp://imgctrl.com/image/AsO&lt;/a&gt; &lt;a href=&quot;\nhttp://imgctrl.com/image/AsT&quot; rel=&quot;nofollow&quot; target=&quot;_NEW&quot;&gt;\nhttp://imgctrl.com/image/AsT&lt;/a&gt; &lt;a href=&quot;\nhttp://imgctrl.com/image/AsV&quot; rel=&quot;nofollow&quot; target=&quot;_NEW&quot;&gt;\nhttp://imgctrl.com/image/AsV&lt;/a&gt; &lt;a href=&quot;\nhttp://imgctrl.com/image/Asb&quot; rel=&quot;nofollow&quot; target=&quot;_NEW&quot;&gt;\nhttp://imgctrl.com/image/Asb&lt;/a&gt; &lt;a href=&quot;\nhttp://imgctrl.com/image/Asl&quot; rel=&quot;nofollow&quot; target=&quot;_NEW&quot;&gt;\nhttp://imgctrl.com/image/Asl&lt;/a&gt; &lt;a href=&quot;\nhttp://imgctrl.com/image/AsG&quot; rel=&quot;nofollow&quot; target=&quot;_NEW&quot;&gt;\nhttp://imgctrl.com/image/AsG&lt;/a&gt; &lt;a href=&quot;\nhttp://imgctrl.com/image/Asp&quot; rel=&quot;nofollow&quot; target=&quot;_NEW&quot;&gt;\nhttp://imgctrl.com/image/Asp&lt;/a&gt; &lt;a href=&quot;\nhttp://imgctrl.com/image/Asv&quot; rel=&quot;nofollow&quot; target=&quot;_NEW&quot;&gt;\nhttp://imgctrl.com/image/Asv&lt;/a&gt; &lt;a href=&quot;\nhttp://imgctrl.com/image/AsD&quot; rel=&quot;nofollow&quot; target=&quot;_NEW&quot;&gt;\nhttp://imgctrl.com/image/AsD&lt;/a&gt; &lt;a href=&quot;\nhttp://imgctrl.com/image/AsP&quot; rel=&quot;nofollow&quot; target=&quot;_NEW&quot;&gt;\nhttp://imgctrl.com/image/AsP&lt;/a&gt; &lt;a href=&quot;\nhttp://imgctrl.com/image/AsW&quot; rel=&quot;nofollow&quot; target=&quot;_NEW&quot;&gt;\nhttp://imgctrl.com/image/AsW&lt;/a&gt; &lt;a href=&quot;\nhttp://imgctrl.com/image/AsX&quot; rel=&quot;nofollow&quot; target=&quot;_NEW&quot;&gt;\nhttp://imgctrl.com/image/AsX&lt;/a&gt; &lt;a href=&quot;\nhttp://imgctrl.com/image/AsQ&quot; rel=&quot;nofollow&quot; target=&quot;_NEW&quot;&gt;\nhttp://imgctrl.com/image/AsQ&lt;/a&gt; &lt;a href=&quot;\nhttp://imgctrl.com/image/AsY&quot; rel=&quot;nofollow&quot; target=&quot;_NEW&quot;&gt;\nhttp://imgctrl.com/image/AsY&lt;/a&gt; &lt;a href=&quot;\nhttp://imgctrl.com/image/Asy&quot; rel=&quot;nofollow&quot; target=&quot;_NEW&quot;&gt;\nhttp://imgctrl.com/image/Asy&lt;/a&gt; &lt;a href=&quot;\nhttp://imgctrl.com/image/Asz&quot; rel=&quot;nofollow&quot; target=&quot;_NEW&quot;&gt;\nhttp://imgctrl.com/image/Asz&lt;/a&gt; &lt;a href=&quot;\nhttp://imgctrl.com/image/A78&quot; rel=&quot;nofollow&quot; target=&quot;_NEW&quot;&gt;\nhttp://imgctrl.com/image/A78&lt;/a&gt; &lt;a href=&quot;\nhttp://imgctrl.com/image/A7A&quot; rel=&quot;nofollow&quot; target=&quot;_NEW&quot;&gt;\nhttp://imgctrl.com/image/A7A&lt;/a&gt; &lt;a href=&quot;\nhttp://imgctrl.com/image/A7C&quot; rel=&quot;nofollow&quot; target=&quot;_NEW&quot;&gt;\nhttp://imgctrl.com/image/A7C&lt;/a&gt; &lt;a href=&quot;\nhttp://imgctrl.com/image/A7N&quot; rel=&quot;nofollow&quot; target=&quot;_NEW&quot;&gt;\nhttp://imgctrl.com/image/A7N&lt;/a&gt; &lt;a href=&quot;\nhttp://imgctrl.com/image/A7a&quot; rel=&quot;nofollow&quot; target=&quot;_NEW&quot;&gt;\nhttp://imgctrl.com/image/A7a&lt;/a&gt; &lt;a href=&quot;\nhttp://imgctrl.com/image/A73&quot; rel=&quot;nofollow&quot; target=&quot;_NEW&quot;&gt;\nhttp://imgctrl.com/image/A73&lt;/a&gt; &lt;a href=&quot;\nhttp://imgctrl.com/image/A7E&quot; rel=&quot;nofollow&quot; target=&quot;_NEW&quot;&gt;\nhttp://imgctrl.com/image/A7E&lt;/a&gt; &lt;a href=&quot;\nhttp://imgctrl.com/image/A7F&quot; rel=&quot;nofollow&quot; target=&quot;_NEW&quot;&gt;\nhttp://imgctrl.com/image/A7F&lt;/a&gt; &lt;a href=&quot;\nhttp://imgctrl.com/image/A7S&quot; rel=&quot;nofollow&quot; target=&quot;_NEW&quot;&gt;\nhttp://imgctrl.com/image/A7S&lt;/a&gt; &lt;a href=&quot;\nhttp://imgctrl.com/image/A7f&quot; rel=&quot;nofollow&quot; target=&quot;_NEW&quot;&gt;\nhttp://imgctrl.com/image/A7f&lt;/a&gt; &lt;a href=&quot;\nhttp://imgctrl.com/image/A7o&quot; rel=&quot;nofollow&quot; target=&quot;_NEW&quot;&gt;\nhttp://imgctrl.com/image/A7o&lt;/a&gt;\n\nVarious shows. Webchat and communications with people on other side, G/G actions, masturbation, you see tits, ass, pussy, etc.\n\nâ˜† Ctrlme Exclusive Torrent List â˜† Daily Updates &lt;a href=&quot;\nhttps://pirates-forum.org/Thread-Ctrlme-Exclusive-Torrent-List&quot; rel=&quot;nofollow&quot; target=&quot;_NEW&quot;&gt;\nhttps://pirates-forum.org/Thread-Ctrlme-Exclusive-Torrent-List&lt;/a&gt;","torrent":{"xt":"urn:btih:c895d66b44dc3f1a22693cdb11e6cf31a3352f50","amp;dn":"MyFreeCams+-+SxyLilith+%5BUpstore+premium%5D","amp;tr":["udp%3A%2F%2Ftracker.openbittorrent.com%3A80","udp%3A%2F%2Fopen.demonii.com%3A1337","udp%3A%2F%2Ftracker.coppersurfer.tk%3A6969","udp%3A%2F%2Fexodus.desync.com%3A6969"],"infoHash":"c895d66b44dc3f1a22693cdb11e6cf31a3352f50","infoHashBuffer":{"type":"Buffer","data":[200,149,214,107,68,220,63,26,34,105,60,219,17,230,207,49,163,53,47,80]},"announce":[],"urlList":[]}}