{"title":"LOVE-157 Amateur JAV CENSORED","uid":12308893,"size":1603090195,"categoryP":"porn","categoryS":"movies","magnet":"?xt=urn:btih:cf68450970dcbf971e05ba011cdccbaf80c93f41&amp;dn=LOVE-157+Amateur+JAV+CENSORED&amp;tr=udp%3A%2F%2Ftracker.openbittorrent.com%3A80&amp;tr=udp%3A%2F%2Fopen.demonii.com%3A1337&amp;tr=udp%3A%2F%2Ftracker.coppersurfer.tk%3A6969&amp;tr=udp%3A%2F%2Fexodus.desync.com%3A6969","seeders":0,"leechers":1,"uploader":"3xplanet","files":1,"time":1440844916,"description":"LOVE-157 Amateur JAV CENSORED\nCover &lt;a href=&quot;\nhttp://www.3xplanet.com/view/106389.html&quot; rel=&quot;nofollow&quot; target=&quot;_NEW&quot;&gt;\nhttp://www.3xplanet.com/view/106389.html&lt;/a&gt;\nScreenshot &lt;a href=&quot;\nhttp://www.3xplanet.com/view/106515.html&quot; rel=&quot;nofollow&quot; target=&quot;_NEW&quot;&gt;\nhttp://www.3xplanet.com/view/106515.html&lt;/a&gt;\nTitle: \nStarring: Amateur\nStudio:  First Star\nTag: JAV, CENSORED, First Star, Small tits, gangbang, Shaved pussy, shyness","torrent":{"xt":"urn:btih:cf68450970dcbf971e05ba011cdccbaf80c93f41","amp;dn":"LOVE-157+Amateur+JAV+CENSORED","amp;tr":["udp%3A%2F%2Ftracker.openbittorrent.com%3A80","udp%3A%2F%2Fopen.demonii.com%3A1337","udp%3A%2F%2Ftracker.coppersurfer.tk%3A6969","udp%3A%2F%2Fexodus.desync.com%3A6969"],"infoHash":"cf68450970dcbf971e05ba011cdccbaf80c93f41","infoHashBuffer":{"type":"Buffer","data":[207,104,69,9,112,220,191,151,30,5,186,1,28,220,203,175,128,201,63,65]},"announce":[],"urlList":[]}}