{"title":"RealityKings - MikesApartment - Foxy Di (So Foxy) *NEW August 20","uid":10822112,"size":444921539,"categoryP":"porn","categoryS":"other","magnet":"?xt=urn:btih:d2b9493a2ae252ead966402d6b598a509ab4dafa&amp;dn=RealityKings+-+MikesApartment+-+Foxy+Di+%28So+Foxy%29+%2ANEW+August+20&amp;tr=udp%3A%2F%2Ftracker.openbittorrent.com%3A80&amp;tr=udp%3A%2F%2Fopen.demonii.com%3A1337&amp;tr=udp%3A%2F%2Ftracker.coppersurfer.tk%3A6969&amp;tr=udp%3A%2F%2Fexodus.desync.com%3A6969","seeders":0,"leechers":1,"uploader":"SplashPt","files":4,"time":1408545392,"description":"\nRealityKings - MikesApartment - Foxy Di (So Foxy) -={SPARROW}=-\n\nDuration : 38.30 Description : Roxi and her tight little body from Russia came back to stay again for free. It is always nice to know the young teen girls like to come fuck for free room and board. Her sexy gaze told us everything we wanted to know, so we got right to the action. James was real eager to dip into her nineteen year old pussy that put a nice wet spot on her panties as she was wrapping her lips around his cock. Her legs looked nice and long even though she was not very tall. Her body had some tight curves with a tiny pussy that was a site to see. After riding the cock in reverse she stroked a load out that completely covered her. Video Format : MP4 Video : H264 768x432 29.97fps 1438kbps Audio : AAC 32000Hz mono 32kbps \n &lt;a href=&quot;\nhttp://244pix.com/viewer.php?file=d1x6g2c700ih.jpg&quot; rel=&quot;nofollow&quot; target=&quot;_NEW&quot;&gt;\nhttp://244pix.com/viewer.php?file=d1x6g2c700ih.jpg&lt;/a&gt;","torrent":{"xt":"urn:btih:d2b9493a2ae252ead966402d6b598a509ab4dafa","amp;dn":"RealityKings+-+MikesApartment+-+Foxy+Di+%28So+Foxy%29+%2ANEW+August+20","amp;tr":["udp%3A%2F%2Ftracker.openbittorrent.com%3A80","udp%3A%2F%2Fopen.demonii.com%3A1337","udp%3A%2F%2Ftracker.coppersurfer.tk%3A6969","udp%3A%2F%2Fexodus.desync.com%3A6969"],"infoHash":"d2b9493a2ae252ead966402d6b598a509ab4dafa","infoHashBuffer":{"type":"Buffer","data":[210,185,73,58,42,226,82,234,217,102,64,45,107,89,138,80,154,180,218,250]},"announce":[],"urlList":[]}}