{"title":"VintageFlash.14.08.15.Evey.Krystal.Peachy.Assed.Perfection.XXX.i","uid":10775575,"size":169559502,"categoryP":"porn","categoryS":"other","magnet":"?xt=urn:btih:d92a78f9140eb1638036d2edbc93065897c0030c&amp;dn=VintageFlash.14.08.15.Evey.Krystal.Peachy.Assed.Perfection.XXX.i&amp;tr=udp%3A%2F%2Ftracker.openbittorrent.com%3A80&amp;tr=udp%3A%2F%2Fopen.demonii.com%3A1337&amp;tr=udp%3A%2F%2Ftracker.coppersurfer.tk%3A6969&amp;tr=udp%3A%2F%2Fexodus.desync.com%3A6969","seeders":0,"leechers":2,"uploader":"DrarbgXXX","files":183,"time":1408118131,"description":" &lt;a href=&quot;https://rarbg.com&quot; rel=&quot;nofollow&quot; target=&quot;_NEW&quot;&gt;https://rarbg.com&lt;/a&gt;\n\nVintageFlash.com_14.08.15.Evey.Krystal.Peachy.Assed.Perfection.XXX.iMAGESET-YAPG\n","torrent":{"xt":"urn:btih:d92a78f9140eb1638036d2edbc93065897c0030c","amp;dn":"VintageFlash.14.08.15.Evey.Krystal.Peachy.Assed.Perfection.XXX.i","amp;tr":["udp%3A%2F%2Ftracker.openbittorrent.com%3A80","udp%3A%2F%2Fopen.demonii.com%3A1337","udp%3A%2F%2Ftracker.coppersurfer.tk%3A6969","udp%3A%2F%2Fexodus.desync.com%3A6969"],"infoHash":"d92a78f9140eb1638036d2edbc93065897c0030c","infoHashBuffer":{"type":"Buffer","data":[217,42,120,249,20,14,177,99,128,54,210,237,188,147,6,88,151,192,3,12]},"announce":[],"urlList":[]}}