{"title":"Nitro Pro 9 -Milaras21- [NAFS]","uid":11969580,"size":374278,"categoryP":"audio","categoryS":"other","magnet":"?xt=urn:btih:f152f50bc9acb61453a01a7bdb0d3842a99728a3&amp;dn=Nitro+Pro+9+-Milaras21-+%5BNAFS%5D&amp;tr=udp%3A%2F%2Ftracker.openbittorrent.com%3A80&amp;tr=udp%3A%2F%2Fopen.demonii.com%3A1337&amp;tr=udp%3A%2F%2Ftracker.coppersurfer.tk%3A6969&amp;tr=udp%3A%2F%2Fexodus.desync.com%3A6969","seeders":0,"leechers":0,"uploader":"Milaras21","files":1,"time":1432775616,"description":"Nitro Pro 9 -Milaras21- [NAFS]\n\nPass: www.newanimaficionados.com","torrent":{"xt":"urn:btih:f152f50bc9acb61453a01a7bdb0d3842a99728a3","amp;dn":"Nitro+Pro+9+-Milaras21-+%5BNAFS%5D","amp;tr":["udp%3A%2F%2Ftracker.openbittorrent.com%3A80","udp%3A%2F%2Fopen.demonii.com%3A1337","udp%3A%2F%2Ftracker.coppersurfer.tk%3A6969","udp%3A%2F%2Fexodus.desync.com%3A6969"],"infoHash":"f152f50bc9acb61453a01a7bdb0d3842a99728a3","infoHashBuffer":{"type":"Buffer","data":[241,82,245,11,201,172,182,20,83,160,26,123,219,13,56,66,169,151,40,163]},"announce":[],"urlList":[]}}