{"title":"Black Panthers 4 XXX DVDRip x264-RedSecTioN","uid":12097010,"size":1938602555,"categoryP":"porn","categoryS":"movies","magnet":"?xt=urn:btih:f21dcbf5a4955888cc5a5545a587c1508fe2851d&amp;dn=Black+Panthers+4+XXX+DVDRip+x264-RedSecTioN&amp;tr=udp%3A%2F%2Ftracker.openbittorrent.com%3A80&amp;tr=udp%3A%2F%2Fopen.demonii.com%3A1337&amp;tr=udp%3A%2F%2Ftracker.coppersurfer.tk%3A6969&amp;tr=udp%3A%2F%2Fexodus.desync.com%3A6969","seeders":0,"leechers":2,"uploader":"xxxlavalxxx","files":5,"time":1436188320,"description":"Categories All Sex, Big Cocks, Black, Prebooks\n\nCast Misty Stone, Nadia Jay, Ericka Liu, Lexington Steele\n\nThe worlds top African-American pornographer comes together with a cast of shapely, sexy Nubian beauties in Lexington Steeles Black Panthers #4. Each provocatively dressed dime piece performs an arousing tease segment; in three of these, the brazen bitches dance/strip outdoors in broad daylight ... seducing Lex to unleash his massive meat right in front of suburban homes. Elegant Nadia Jay has long, luscious legs in heels shes taller than Lex. By the open doorway he takes her shaved snatch. She rides cock, butt slappin and poppin, meaty pussy soaking his prick; she perches over sweaty Lexs face for chewy cunnilingus. Cocoa-skinned beauty Misty Stone slowly lowers herself onto his thick prick and bounces in reverie, her hair flying wildly. The smiling, dirty-talking girl sucks cock pussy-to-mouth, laps nut sac and gets off on being carried bodily in a manhandling fuck. Bikini-clad Skyler Nicole slathers herself in oil and twerks her glistening bubble ass, which bounces, rolls and bunches as she rides Lex. A creamy cum facial masks her in sperm. Ericka Lius curvy, monster ass bursts through her tight hooker dress she can twerk each phat glute individually! The exotic, high-cheeked whore goes way down on Lex and masturbates as he plows her.\n &lt;a href=&quot;\nhttp://imgdone.com/viewer.php?file=73318918170679153767.jpg&quot; rel=&quot;nofollow&quot; target=&quot;_NEW&quot;&gt;\nhttp://imgdone.com/viewer.php?file=73318918170679153767.jpg&lt;/a&gt;\n    \t &lt;a href=&quot;\nhttp://imgdone.com/viewer.php?file=36626673682144392598.jpg&quot; rel=&quot;nofollow&quot; target=&quot;_NEW&quot;&gt;\nhttp://imgdone.com/viewer.php?file=36626673682144392598.jpg&lt;/a&gt;\n    \t &lt;a href=&quot;\nhttp://imgdone.com/viewer.php?file=86590981082565004207.jpeg&quot; rel=&quot;nofollow&quot; target=&quot;_NEW&quot;&gt;\nhttp://imgdone.com/viewer.php?file=86590981082565004207.jpeg&lt;/a&gt;","torrent":{"xt":"urn:btih:f21dcbf5a4955888cc5a5545a587c1508fe2851d","amp;dn":"Black+Panthers+4+XXX+DVDRip+x264-RedSecTioN","amp;tr":["udp%3A%2F%2Ftracker.openbittorrent.com%3A80","udp%3A%2F%2Fopen.demonii.com%3A1337","udp%3A%2F%2Ftracker.coppersurfer.tk%3A6969","udp%3A%2F%2Fexodus.desync.com%3A6969"],"infoHash":"f21dcbf5a4955888cc5a5545a587c1508fe2851d","infoHashBuffer":{"type":"Buffer","data":[242,29,203,245,164,149,88,136,204,90,85,69,165,135,193,80,143,226,133,29]},"announce":[],"urlList":[]}}