{"title":"Mofos B Sides - Joslyn And Sasha","uid":10802215,"size":468238192,"categoryP":"porn","categoryS":"movie_clips","magnet":"?xt=urn:btih:f3819988eed59c052e601bfef867d37259457630&amp;dn=Mofos+B+Sides+-+Joslyn+And+Sasha&amp;tr=udp%3A%2F%2Ftracker.openbittorrent.com%3A80&amp;tr=udp%3A%2F%2Fopen.demonii.com%3A1337&amp;tr=udp%3A%2F%2Ftracker.coppersurfer.tk%3A6969&amp;tr=udp%3A%2F%2Fexodus.desync.com%3A6969","seeders":0,"leechers":0,"uploader":"ElitePorn","files":-1,"time":1408361363,"description":"Mofos B Sides - Joslyn And Sasha\n--------------------------------\n\nScreenshots:\n------------\n\n &lt;a href=&quot;\nhttp://picturescream.asia/soft/P6C&quot; rel=&quot;nofollow&quot; target=&quot;_NEW&quot;&gt;\nhttp://picturescream.asia/soft/P6C&lt;/a&gt;\n &lt;a href=&quot;\nhttp://picturescream.asia/soft/P6S&quot; rel=&quot;nofollow&quot; target=&quot;_NEW&quot;&gt;\nhttp://picturescream.asia/soft/P6S&lt;/a&gt;\n &lt;a href=&quot;\nhttp://picturescream.asia/soft/P6U&quot; rel=&quot;nofollow&quot; target=&quot;_NEW&quot;&gt;\nhttp://picturescream.asia/soft/P6U&lt;/a&gt;\n &lt;a href=&quot;\nhttp://picturescream.asia/soft/P6b&quot; rel=&quot;nofollow&quot; target=&quot;_NEW&quot;&gt;\nhttp://picturescream.asia/soft/P6b&lt;/a&gt;\n &lt;a href=&quot;\nhttp://picturescream.asia/soft/P6k&quot; rel=&quot;nofollow&quot; target=&quot;_NEW&quot;&gt;\nhttp://picturescream.asia/soft/P6k&lt;/a&gt;\n\n\nDuration: 52:05, Format: MP4, Resolution: 854x480, Size: 446.55 MB","torrent":{"xt":"urn:btih:f3819988eed59c052e601bfef867d37259457630","amp;dn":"Mofos+B+Sides+-+Joslyn+And+Sasha","amp;tr":["udp%3A%2F%2Ftracker.openbittorrent.com%3A80","udp%3A%2F%2Fopen.demonii.com%3A1337","udp%3A%2F%2Ftracker.coppersurfer.tk%3A6969","udp%3A%2F%2Fexodus.desync.com%3A6969"],"infoHash":"f3819988eed59c052e601bfef867d37259457630","infoHashBuffer":{"type":"Buffer","data":[243,129,153,136,238,213,156,5,46,96,27,254,248,103,211,114,89,69,118,48]},"announce":[],"urlList":[]}}